{"cameraMode":{"drawMode":0,"name":"Shaded","section":"Shading Mode"},"sceneLighting":true,"audioPlay":false,"sceneViewState":{"m_AlwaysRefresh":false,"showFog":true,"showSkybox":true,"showFlares":true,"showImageEffects":true,"showParticleSystems":true,"showVisualEffectGraphs":true,"m_FxEnabled":true},"in2DMode":false,"pivot":{"x":-11.571475982666016,"y":-2.015361785888672,"z":5.6570892333984379},"rotation":{"x":-0.23896199464797975,"y":0.19276560842990876,"z":-0.04846423491835594,"w":-0.9504696726799011},"size":31.411745071411134,"orthographic":false}